empirestaterunup/__init__.py
empirestaterunup/analyze.py
empirestaterunup/apps.py
empirestaterunup/browser.tcss
empirestaterunup/country_codes.toml
empirestaterunup/data.py
empirestaterunup/five_numbers.tcss
empirestaterunup/metadata-2023.json
empirestaterunup/metadata-2024.json
empirestaterunup/outliers.tcss
empirestaterunup/providers.py
empirestaterunup/results-2023.json
empirestaterunup/results-2024.json
empirestaterunup/runner_details.tcss
empirestaterunup/runners.py
empirestaterunup/screens.py
empirestaterunup/server.py
empirestaterunup-2025.0.3.dist-info/licenses/LICENSE
images/age_histogram.png
images/age_plot.png
images/empire_state_runup.png
images/esrm_outlier_first_screen.png
images/esrm_outlier_runner_detail.png
images/esru_age_box_plot.png
images/esru_browser.png
images/esru_numbers.svg
images/esru_outlier-1.svg
images/esru_outlier-2.svg
images/gender_distribution.png
images/participants_per_country.png
images/race_runners_2023-12-31T18_35_53_558956.svg
empirestaterunup-2025.0.3.dist-info/METADATA
empirestaterunup-2025.0.3.dist-info/WHEEL
empirestaterunup-2025.0.3.dist-info/entry_points.txt
empirestaterunup-2025.0.3.dist-info/top_level.txt
empirestaterunup-2025.0.3.dist-info/RECORD
