Metadata-Version: 2.4
Name: EmpireStateRunUp
Version: 2025.0.3
Summary: Collection of scripts to analyze the results of the Empire State Run Up race
Author-email: Jose Vicente Nunez <kodegeek.com@protonmail.com>
License:                                  Apache License
Keywords: running,race,empire state,tower racing
Classifier: Environment :: Console
Classifier: Development Status :: 5 - Production/Stable
Classifier: Programming Language :: Python :: 3.11
Classifier: Intended Audience :: End Users/Desktop
Classifier: Topic :: Utilities
Requires-Python: >=3.11
License-File: LICENSE
Requires-Dist: pandas==2.2.3
Requires-Dist: textual==3.7.1
Requires-Dist: textual-serve==1.1.1
Requires-Dist: rich==13.9.4
Requires-Dist: numpy==1.26.4
Requires-Dist: matplotlib==3.10.0
Requires-Dist: tomlkit==0.13.2
Provides-Extra: lint
Requires-Dist: ruff==0.12.0; extra == "lint"
Requires-Dist: yamllint==1.28.0; extra == "lint"
Provides-Extra: dev
Requires-Dist: textual-dev==1.7.0; extra == "dev"
Requires-Dist: twine==6.1.0; extra == "dev"
Requires-Dist: build; extra == "dev"
Dynamic: license-file
